{
  "slug": "reforma-banheiro-moderno-2026",
  "title": "Reforma de Banheiro Moderno: Tendências e Custos 2026",
  "excerpt": "Como planejar a reforma do banheiro com estilo spa, tecnologia e sustentabilidade.",
  "category": "Reforma",
  "tags": [
    "banheiro",
    "reforma",
    "spa",
    "sustentabilidade"
  ],
  "content": "# Reforma de Banheiro Moderno: Tendências e Custos 2026\n\nO banheiro deixou de ser apenas funcional para se tornar um espaço de bem-estar e relaxamento. Veja como criar seu spa pessoal.\n\n## Tendências 2026\n\n### Conceito Spa\nTransforme seu banheiro em refúgio de autocuidado.\n\n**Elementos:**\n- Banheira de imersão\n- Chuveiro de chuva\n- Iluminação relaxante\n- Pedras naturais\n- Plantas tropicais\n- Aquecimento de piso\n- Aromaterapia integrada\n\n### Sustentabilidade\n- Torneiras com arejador\n- Descarga dual flush\n- Chuveiro com temporizador\n- Reúso de água cinza\n- Iluminação LED\n- Materiais reciclados\n\n### Tecnologia\n- Espelho com desembaçador\n- Espelho com iluminação LED\n- Vaso sanitário inteligente\n- Chuveiro digital\n- Música ambiente\n- Controle por app\n\n## Custos de Reforma\n\n### Banheiro Básico (R$ 8.000 - R$ 15.000)\n- Revestimento cerâmico\n- Louças brancas padrão\n- Metais cromados simples\n- Box de vidro temperado\n- Iluminação básica\n\n### Banheiro Intermediário (R$ 15.000 - R$ 35.000)\n- Porcelanato retificado\n- Louças de design\n- Metais com acabamento especial\n- Nicho embutido\n- Iluminação indireta\n- Bancada de mármore ou quartzo\n\n### Banheiro Alto Padrão (R$ 35.000 - R$ 80.000+)\n- Mármore ou pedras nobres\n- Louças premium (Deca, Roca)\n- Metais importados\n- Banheira de hidromassagem\n- Chuveiro de chuva + ducha\n- Aquecimento de piso\n- Automação\n\n## Materiais em Alta\n\n### Revestimentos\n- Porcelanato efeito mármore\n- Pedras naturais\n- Cimento queimado\n- Pastilhas de vidro\n- Madeira tratada\n\n### Louças\n- Brancas sempre clássicas\n- Preto fosco moderno\n- Cinza concreto\n- Formas orgânicas\n\n### Metais\n- Preto fosco\n- Dourado rosé\n- Bronze envelhecido\n- Inox escovado\n\n## Tamanhos e Layouts\n\n### Lavabo (2-3m²)\nEssenciais: vaso e cuba\nOpcional: espelho grande, revestimento de destaque\n\n### Banheiro Social (4-6m²)\nEssenciais: vaso, chuveiro, cuba\nLayout: linear ou em L\n\n### Suíte (6-10m²)\nEssenciais: vaso, chuveiro, cuba dupla\nOpcional: banheira, closet integrado\n\n### Suíte Máster (10-20m²)\nCompleto: duplo de tudo, banheira, closet, área de maquiagem\n\n## Passo a Passo da Reforma\n\n### 1. Planejamento\n- Definir layout\n- Escolher materiais\n- Orçamento detalhado\n- Projeto 3D\n\n### 2. Demolição (2-3 dias)\n- Remoção de louças\n- Quebra de revestimentos\n- Ponto de descarte\n\n### 3. Infraestrutura (5-7 dias)\n- Impermeabilização\n- Instalação hidráulica\n- Instalação elétrica\n- Pontos de iluminação\n\n### 4. Revestimentos (7-10 dias)\n- Contrapiso\n- Piso\n- Azulejos/porcelanato\n- Rejuntamento\n\n### 5. Instalações (3-5 dias)\n- Louças\n- Metais\n- Box\n- Bancada\n- Espelhos\n\n### 6. Acabamentos (2-3 dias)\n- Iluminação\n- Acessórios\n- Pintura\n- Limpeza\n\n**Prazo total: 3 a 5 semanas**\n\n## Erros Comuns\n\n❌ Esquecer impermeabilização adequada\n❌ Não planejar ventilação\n❌ Escolher materiais escorregadios para piso\n❌ Economizar em materiais hidráulicos\n❌ Não testar pressão da água\n\n## Dicas Importantes\n\n✅ Use piso antiderrapante\n✅ Planeje iluminação em camadas\n✅ Invista em boa ventilação\n✅ Preveja tomadas suficientes\n✅ Escolha materiais fáceis de limpar\n✅ Teste todo instalação antes do acabamento\n\n## Banheiros Pequenos\n\nSoluções para aproveitar cada centímetro:\n\n- Cuba de sobrepor com gabinete\n- Vaso sanitário suspenso\n- Box com porta de correr\n- Espelho grande\n- Nicho no box\n- Prateleiras suspensas\n- Cores claras\n\n## Acessibilidade\n\nPense no futuro:\n\n- Barras de apoio\n- Piso antiderrapante\n- Banco no box\n- Torneiras monocomando\n- Iluminação adequada\n- Espaço para manobra\n\n## Grupo WG Almeida - Reforma de Banheiros\n\nNossa especialidade:\n\n✅ Impermeabilização com garantia\n✅ Materiais de primeira linha\n✅ Instalação hidráulica certificada\n✅ Projeto 3D realista\n✅ Prazo cumprido\n✅ Garantia de 5 anos\n\n**Transforme seu banheiro em spa!**",
  "date": "2026-01-25",
  "author": "Grupo WG Almeida",
  "image": "/images/blog/reforma-banheiro-moderno-2026.jpg"
}