{
  "slug": "reforma-banheiro-pequeno-otimizacao",
  "title": "Reforma de Banheiro Pequeno: 20 Dicas para Otimizar Espaço",
  "excerpt": "Transforme seu banheiro pequeno com soluções inteligentes: layout, cores, revestimentos, louças e truques que ampliam visualmente.",
  "date": "2026-01-25",
  "author": "Grupo WG Almeida",
  "category": "Reforma",
  "tags": ["banheiro pequeno", "reforma banheiro", "otimização", "espaço"],
  "image": "/images/blog/banheiro-pequeno.jpg",
  "content": "# Reforma de Banheiro Pequeno: 20 Dicas para Otimizar\n\n## Entendendo Banheiro Pequeno\n\n### Tamanhos\n**Muito pequeno:** <2,5m² (lavabo)\n**Pequeno:** 2,5-4m²\n**Médio:** 4-6m²\n**Grande:** 6m²+\n\n### Desafios\n❌ Pouco espaço circulação\n❌ Sensação claustrofóbica\n❌ Dificulta armazenamento\n❌ Limitações layout\n\n### Soluções\n✅ Layout inteligente\n✅ Cores claras\n✅ Iluminação adequada\n✅ Louças compactas\n✅ Espelhos estratégicos\n\n## 20 Dicas de Otimização\n\n### 1. Layout Otimizado\n\n**Regra de Ouro:**\n- Pia próxima à porta\n- Vaso ao fundo\n- Box lateral\n- Circulação mínima 60cm\n\n**Distribuição:**\n- Porta abre para fora (economiza espaço)\n- Aproveitar cantos\n- Alinhamento estratégico\n\n### 2. Louças Suspensas\n\n**Vaso suspenso:**\n✅ Facilita limpeza\n✅ Sensação amplitude\n✅ Modernidade\n+ R$ 400-800 vs comum\n\n**Cuba suspensa:**\n✅ Mais espaço embaixo\n✅ Limpa visualmente\n✅ Contemporânea\n\n### 3. Box Sem Perfil\n\n**Vidro incolor:**\n- 8mm temperado\n- Sem perfis (ou mínimos)\n- Transparência total\n- Amplia visualmente 40%\n\n**Custo:** R$ 800-1.500/m²\n\n### 4. Cores Claras\n\n**Paredes:**\n- Branco\n- Off-white\n- Bege clarinho\n- Cinza claro\n\n**Revestimentos:**\n- Porcelanato branco\n- Mármore Carrara\n- Cimento claro\n\n**Evitar:**\n❌ Cores escuras (>30% área)\n❌ Muitos padrões\n\n### 5. Espelhos Grandes\n\n**Regra:**\n- Quanto maior, melhor\n- Parede inteira ideal\n- Mínimo: 80cm largura\n\n**Posicionamento:**\n- Sobre pia (óbvio)\n- Parede lateral (duplica)\n- Atrás porta (amplia)\n\n**Ampliação visual:** +60-100%\n\n### 6. Iluminação Abundante\n\n**Natural:**\n- Janela máxima possível\n- Vidro jateado (privacidade)\n- Claraboia (se viável)\n\n**Artificial:**\n- Spots distribuídos (20-25W/m²)\n- 4000K (branca neutra)\n- LED fita no espelho\n- Iluminação indireta\n\n### 7. Nichos Embutidos\n\n**Onde:**\n- Parede box (produtos)\n- Sobre vaso (decoração)\n- Lateral pia (toalhas)\n\n**Dimensões:**\n- 30x30cm (padrão)\n- 15cm profundidade\n- LED integrado\n\n### 8. Porta de Correr\n\n**Economia:**\n- 90cm espaço abertura\n- Permite pia maior\n- Moderniza\n\n**Tipos:**\n- Externa (mais fácil)\n- Embutida (mais limpa)\n\n**Custo:** R$ 800-2.500\n\n### 9. Cuba Pequena\n\n**Opções:**\n- 30x30cm (mínimo)\n- 35x35cm (confortável)\n- Quadrada ou retangular\n- Suspensa ou semi-encaixe\n\n**Evitar:**\n❌ Cubas grandes (>45cm)\n❌ Duplas (desperdício)\n\n### 10. Marcenaria Sob Medida\n\n**Vantagens:**\n✅ Aproveita cada cm\n✅ Personalizada\n✅ Gavetas otimizadas\n\n**Incluir:**\n- Gaveta organizada\n- Nicho papel higiênico\n- Toalheiro integrado\n- Cesto embutido\n\n**Custo:** R$ 2.000-6.000\n\n### 11. Revestimento Grande Formato\n\n**Porcelanato:**\n- 60x120cm\n- 90x90cm\n- Menos juntas\n- Continuidade visual\n\n**Evitar:**\n❌ Mosaicos pequenos\n❌ Muitas cores\n❌ Padrões complexos\n\n### 12. Teto Alto (Amplitude Vertical)\n\n**Se pé-direito permite:**\n- Não rebaixar teto todo\n- Rebaixo apenas perímetro\n- Forro branco\n\n**Iluminação:**\n- Embutida no rebaixo\n- Iluminação indireta\n\n### 13. Prateleiras de Vidro\n\n**Vantagens:**\n✅ Não pesam visualmente\n✅ Transparentes\n✅ Modernas\n\n**Onde:**\n- Sobre pia\n- Cantos\n- Entre nichos\n\n**Custo:** R$ 100-300/peça\n\n### 14. Chuveiro Teto\n\n**Benefícios:**\n✅ Luxuoso\n✅ Não ocupa parede\n✅ Limpeza visual\n\n**Atenção:**\n- Pressão adequada (20 mca)\n- Instalação teto\n- Manutenção complexa\n\n**Custo:** R$ 500-3.000\n\n### 15. Ventilação/Exaustão\n\n**Essencial:**\n- Exaustor (se sem janela)\n- Extrai umidade\n- Evita mofo\n\n**Tipos:**\n- Axial: R$ 150-400\n- Centrífugo: R$ 300-800\n- Silencioso: +50%\n\n### 16. Porta Toalha Aquecida\n\n**Vantagens:**\n✅ Toalha sempre seca\n✅ Funcional + luxo\n✅ Ocupa parede\n\n**Custo:** R$ 400-1.500\n\n### 17. Vaso Sanitário Compacto\n\n**Medidas especiais:**\n- Comprimento: 45-50cm (vs 55-60cm comum)\n- Economia: 10-15cm\n- Mesma funcionalidade\n\n**Marcas:**\n- Deca: Linha Petit\n- Incepa: Compacto\n- Roca: Mini\n\n**Custo:** R$ 400-1.200\n\n### 18. Ralo Linear\n\n**Vantagens:**\n✅ Drena melhor\n✅ Estética limpa\n✅ Instalação discreta\n\n**Onde:**\n- Box inteiro\n- Entrada box\n- Centro (se necessário)\n\n**Custo:** R$ 300-800\n\n### 19. Torneira Parede\n\n**Economia:**\n- Libera bancada\n- Limpeza mais fácil\n- Modernidade\n\n**Atenção:**\n- Ponto hidráulico na parede\n- Planejar na obra\n\n**Custo:** +R$ 200-500 vs bancada\n\n### 20. Decoração Minimalista\n\n**Menos é mais:**\n✅ Poucos objetos\n✅ Cores neutras\n✅ Linhas limpas\n✅ Funcionalidade\n\n**Evitar:**\n❌ Muitos quadros\n❌ Objetos decorativos\n❌ Tapetes grandes\n❌ Cortinas pesadas\n\n## Erros Comuns\n\n### 1. Cores Escuras\n- Reduz visualmente 30-40%\n- Claustrofóbico\n- Solução: Máx 30% área escura\n\n### 2. Box Colorido/Fosco\n- Bloqueia visão\n- Reduz sensação espaço\n- Solução: Vidro incolor\n\n### 3. Muitos Padrões\n- Visual poluído\n- Cansa\n- Solução: Máx 2 materiais destaque\n\n### 4. Iluminação Insuficiente\n- Escuro = pequeno\n- Solução: 20-25W/m² LED\n\n### 5. Móveis Grandes\n- Ocupam espaço\n- Circulação ruim\n- Solução: Sob medida compacto\n\n## Truques Visuais\n\n### Listras Verticais\n- Revestimento vertical\n- Alonga parede\n- Aumenta pé-direito visual\n\n### Continuidade Piso\n\n- Mesmo piso quarto/banheiro\n- Amplia visualmente\n- Fluidez espacial\n\n### Espelho Frente Janela\n- Reflete luz natural\n- Duplica iluminação\n- Sensação amplitude\n\n### Prateleiras Altas\n- Usa espaço vertical\n- Não atrapalha circulação\n- Armazena sem pesar\n\n## Materiais Recomendados\n\n### Revestimentos\n**Porcelanato:**\n- Branco Carrara\n- Cimento claro\n- Mármore branco\n- 60x120cm ou maior\n\n**Custo:** R$ 80-250/m²\n\n### Louças\n**Marcas:**\n- Deca (custo-benefício)\n- Deca Black (premium nacional)\n- Roca (importada)\n- Duravit (luxo)\n\n**Conjunto básico:**\n- Vaso: R$ 400-1.500\n- Cuba: R$ 300-1.200\n- Metais: R$ 600-2.500\n\n### Metais\n**Acabamentos 2026:**\n- Preto fosco (tendência)\n- Dourado escovado\n- Inox escovado\n- Cromado (clássico)\n\n## Custos Reforma\n\n### Banheiro 3m²\n\n**Econômica (R$ 8.000-15.000):**\n- Demolição: R$ 800\n- Instalações: R$ 2.500\n- Revestimentos: R$ 2.500\n- Louças básicas: R$ 1.500\n- Metais: R$ 800\n- Box: R$ 1.200\n- Mão de obra: R$ 3.000\n\n**Intermediária (R$ 18.000-30.000):**\n- Demolição: R$ 1.000\n- Instalações: R$ 3.500\n- Porcelanato premium: R$ 4.500\n- Louças suspensas: R$ 3.000\n- Metais preto fosco: R$ 2.000\n- Box incolor 8mm: R$ 2.500\n- Marcenaria: R$ 3.000\n- Iluminação: R$ 1.500\n- Mão de obra: R$ 5.000\n\n**Premium (R$ 35.000-60.000):**\n- Demolição: R$ 1.200\n- Instalações completas: R$ 5.000\n- Mármore Carrara: R$ 10.000\n- Louças Duravit: R$ 6.000\n- Metais Deca Black: R$ 4.000\n- Box sob medida: R$ 4.000\n- Marcenaria premium: R$ 6.000\n- Iluminação + automação: R$ 3.000\n- Mão de obra: R$ 7.000\n\n## Prazo\n\n**Banheiro 3-4m²:**\n- Demolição: 1 dia\n- Instalações: 5-7 dias\n- Contrapiso: 2 dias + 3 cura\n- Revestimentos: 5-7 dias\n- Rejunte: 1 dia\n- Pintura: 2 dias\n- Instalações finais: 2 dias\n- Limpeza: 1 dia\n\n**Total:** 25-35 dias\n\n## Checklist\n\n- [ ] Medir espaço exato\n- [ ] Definir layout otimizado\n- [ ] Escolher cores claras\n- [ ] Especificar louças compactas\n- [ ] Box vidro incolor\n- [ ] Espelho grande\n- [ ] Iluminação 20-25W/m²\n- [ ] Nicho embutido\n- [ ] Ventilação adequada\n- [ ] Orçar 3 fornecedores\n\n## Conclusão\n\nBanheiro pequeno bem planejado:\n✅ Parece 40-60% maior\n✅ Funcional\n✅ Confortável\n✅ Valoriza imóvel\n\n**Investimento:** R$ 8.000-60.000 (3m²)\n**Priorizar:**\n1. Layout inteligente\n2. Cores claras\n3. Iluminação abundante\n4. Espelhos grandes\n5. Louças compactas"
}
